Workbook

Sheet Cleaned Data
A1: Date | B1: Category | C1: Description | D1: Amount | E1: Payment_Mode | F1: Year | G1: Month
A2: 2024-01-01 | B2: Rent | C2: House rent | D2: 10983 | E2: UPI | F2: 2024 | G2: January
A3: 2024-01-02 | B3: Unknown | C3: Electronics | D3: 4300 | E3: Credit Card | F3: 2024 | G3: January
A4: 2024-01-02 | B4: Shopping | C4: Myntra purchase | D4: 2645 | E4: UPI | F4: 2024 | G4: January
A5: 2024-01-04 | B5: Rent | C5: House rent | D5: 9173 | E5: Credit Card | F5: 2024 | G5: January
A6: 2024-01-16 | B6: Shopping | C6: Clothes shopping | D6: 4545 | E6: Cash | F6: 2024 | G6: January
A7: 2024-01-17 | B7: Healthcare | C7: Health checkup | D7: 989 | E7: Cash | F7: 2024 | G7: January
A8: 2024-01-17 | B8: Education | C8: Tuition fee | D8: 1267 | E8: Credit Card | F8: 2024 | G8: January
A9: 2024-01-17 | B9: Healthcare | C9: Health checkup | D9: 1280 | E9: Debit Card | F9: 2024 | G9: January
A10: 2024-01-17 | B10: Food | C10: Zomato order | D10: 172 | E10: Credit Card | F10: 2024 | G10: January
A11: 2024-01-18 | B11: Food | C11: Cafe coffee | D11: 234 | E11: Debit Card | F11: 2024 | G11: January
A12: 2024-01-23 | B12: Other | C12: ATM withdrawal | D12: 796 | E12: Credit Card | F12: 2024 | G12: January
A13: 2024-01-23 | B13: Groceries | C13: Monthly groceries | D13: 1666 | E13: Credit Card | F13: 2024 | G13: January
... A217: 2024-12-08 | B217: Rent | C217: House rent | D217: 11839 | E217: Debit Card | F217: 2024 | G217: December

Sheet Chart Data
A1: Category | B1: Total Spend | D1: Month | E1: Total Spend | G1: Payment Mode | H1: Total Spend | J1: Category | K1: Txn Count | M1: Description | N1: Amount
A2: Education | B2: =ROUND(SUMIF('Cleaned Data'!B2:B217,A2,'Cleaned Data'!D2:D217),2) -> 63527 | D2: January | E2: =ROUND(SUMIF('Cleaned Data'!G2:G217,D2,'Cleaned Data'!D2:D217),2) -> 45912 | G2: Cash | H2: =ROUND(SUMIF('Cleaned Data'!E2:E217,G2,'Cleaned Data'!D2:D217),2) -> 109886 | J2: Education | K2: =COUNTIF('Cleaned Data'!B2:B217,J2) -> 25 | M2: Not specified | N2: 14764
A3: Entertainment | B3: =ROUND(SUMIF('Cleaned Data'!B2:B217,A3,'Cleaned Data'!D2:D217),2) -> 14321 | D3: February | E3: =ROUND(SUMIF('Cleaned Data'!G2:G217,D3,'Cleaned Data'!D2:D217),2) -> 41521 | G3: Credit Card | H3: =ROUND(SUMIF('Cleaned Data'!E2:E217,G3,'Cleaned Data'!D2:D217),2) -> 115428 | J3: Entertainment | K3: =COUNTIF('Cleaned Data'!B2:B217,J3) -> 28 | M3: House rent | N3: 13925
A4: Food | B4: =ROUND(SUMIF('Cleaned Data'!B2:B217,A4,'Cleaned Data'!D2:D217),2) -> 8304 | D4: March | E4: =ROUND(SUMIF('Cleaned Data'!G2:G217,D4,'Cleaned Data'!D2:D217),2) -> 45972 | G4: Debit Card | H4: =ROUND(SUMIF('Cleaned Data'!E2:E217,G4,'Cleaned Data'!D2:D217),2) -> 51606 | J4: Food | K4: =COUNTIF('Cleaned Data'!B2:B217,J4) -> 19 | M4: House rent | N4: 13771
A5: Groceries | B5: =ROUND(SUMIF('Cleaned Data'!B2:B217,A5,'Cleaned Data'!D2:D217),2) -> 31338 | D5: April | E5: =ROUND(SUMIF('Cleaned Data'!G2:G217,D5,'Cleaned Data'!D2:D217),2) -> 33246 | G5: UPI | H5: =ROUND(SUMIF('Cleaned Data'!E2:E217,G5,'Cleaned Data'!D2:D217),2) -> 159352 | J5: Groceries | K5: =COUNTIF('Cleaned Data'!B2:B217,J5) -> 24 | M5: Monthly rent | N5: 13587
A6: Healthcare | B6: =ROUND(SUMIF('Cleaned Data'!B2:B217,A6,'Cleaned Data'!D2:D217),2) -> 29843 | D6: May | E6: =ROUND(SUMIF('Cleaned Data'!G2:G217,D6,'Cleaned Data'!D2:D217),2) -> 42144 | G6: Unknown | H6: =ROUND(SUMIF('Cleaned Data'!E2:E217,G6,'Cleaned Data'!D2:D217),2) -> 9281 | J6: Healthcare | K6: =COUNTIF('Cleaned Data'!B2:B217,J6) -> 18 | M6: House rent | N6: 12594
A7: Other | B7: =ROUND(SUMIF('Cleaned Data'!B2:B217,A7,'Cleaned Data'!D2:D217),2) -> 13242 | D7: June | E7: =ROUND(SUMIF('Cleaned Data'!G2:G217,D7,'Cleaned Data'!D2:D217),2) -> 22107 | J7: Other | K7: =COUNTIF('Cleaned Data'!B2:B217,J7) -> 15
A8: Rent | B8: =ROUND(SUMIF('Cleaned Data'!B2:B217,A8,'Cleaned Data'!D2:D217),2) -> 176405 | D8: July | E8: =ROUND(SUMIF('Cleaned Data'!G2:G217,D8,'Cleaned Data'!D2:D217),2) -> 59378 | J8: Rent | K8: =COUNTIF('Cleaned Data'!B2:B217,J8) -> 15
A9: Shopping | B9: =ROUND(SUMIF('Cleaned Data'!B2:B217,A9,'Cleaned Data'!D2:D217),2) -> 68475 | D9: August | E9: =ROUND(SUMIF('Cleaned Data'!G2:G217,D9,'Cleaned Data'!D2:D217),2) -> 35357 | J9: Shopping | K9: =COUNTIF('Cleaned Data'!B2:B217,J9) -> 32
A10: Transport | B10: =ROUND(SUMIF('Cleaned Data'!B2:B217,A10,'Cleaned Data'!D2:D217),2) -> 5045 | D10: September | E10: =ROUND(SUMIF('Cleaned Data'!G2:G217,D10,'Cleaned Data'!D2:D217),2) -> 42369 | J10: Transport | K10: =COUNTIF('Cleaned Data'!B2:B217,J10) -> 14
A11: Unknown | B11: =ROUND(SUMIF('Cleaned Data'!B2:B217,A11,'Cleaned Data'!D2:D217),2) -> 11145 | D11: October | E11: =ROUND(SUMIF('Cleaned Data'!G2:G217,D11,'Cleaned Data'!D2:D217),2) -> 59635 | J11: Unknown | K11: =COUNTIF('Cleaned Data'!B2:B217,J11) -> 6
A12: Utilities | B12: =ROUND(SUMIF('Cleaned Data'!B2:B217,A12,'Cleaned Data'!D2:D217),2) -> 23908 | D12: November | E12: =ROUND(SUMIF('Cleaned Data'!G2:G217,D12,'Cleaned Data'!D2:D217),2) -> 4961 | J12: Utilities | K12: =COUNTIF('Cleaned Data'!B2:B217,J12) -> 20
D13: December | E13: =ROUND(SUMIF('Cleaned Data'!G2:G217,D13,'Cleaned Data'!D2:D217),2) -> 12951

Sheet Dashboard

Sheet How It Was Cleaned
A1: DATA CLEANING SUMMARY
A4: Raw file | B4: expenses_raw.csv — 230 rows with real-world messy data.
A5: Cleaned file | B5: expenses_cleaned.csv — 216 rows after cleaning (see clean_data.py).
A7: Cleaning steps performed:
A8: 1. Removed duplicates | B8: 10 exact duplicate rows dropped using drop_duplicates().
A9: 2. Fixed Category text | B9: Trimmed whitespace, standardized casing (str.strip().str.title()), fixed typos with a mapping dictionary.
A10: 3. Fixed Payment_Mode text | B10: Same cleanup approach as Category.
A11: 4. Cleaned Amount column | B11: Removed currency symbols (₹, Rs.), fixed comma-as-decimal formatting, removed negative signs, converted to float.
A12: 5. Parsed mixed Date formats | B12: Used pd.to_datetime(..., format='mixed') to handle DD-MM-YYYY, MM/DD/YYYY, and YYYY-MM-DD all in one column.
A13: 6. Handled missing values | B13: Dropped rows missing Amount or Date (unusable for analysis); filled missing Category/Description/Payment_Mode with 'Unknown'/'Not specified'.
A14: 7. Added derived columns | B14: Extracted Year and Month from Date for easier grouping.
A16: Tip for interview: | B16: Explain the difference between dropping vs filling missing values, and why: some missing values make a row unusable (Amount, Date), while others can be safely labeled 'Unknown'.
